Metadata-Version: 2.4
Name: openmux
Version: 0.2.2
Summary: A free multi-source GenAI orchestration library for automatic model selection and routing
Author-email: Md Nizamuddin <mdnu838@gmail.com>
Maintainer-email: Md Nizamuddin <mdnu838@gmail.com>
License: MIT
Project-URL: Homepage, https://github.com/mdnu838/OpenMux
Project-URL: Documentation, https://github.com/mdnu838/OpenMux/tree/main/docs
Project-URL: Repository, https://github.com/mdnu838/OpenMux
Project-URL: Issues, https://github.com/mdnu838/OpenMux/issues
Project-URL: Changelog, https://github.com/mdnu838/OpenMux/blob/main/CHANGELOG.md
Keywords: ai,llm,genai,model-selection,orchestration,free-models,openmux
Classifier: Development Status :: 3 - Alpha
Classifier: Intended Audience :: Developers
Classifier: License :: OSI Approved :: MIT License
Classifier: Programming Language :: Python :: 3
Classifier: Programming Language :: Python :: 3.9
Classifier: Programming Language :: Python :: 3.10
Classifier: Programming Language :: Python :: 3.11
Classifier: Programming Language :: Python :: 3.12
Classifier: Topic :: Scientific/Engineering :: Artificial Intelligence
Requires-Python: >=3.9
License-File: LICENSE
Requires-Dist: pydantic>=2.0.0
Requires-Dist: transformers>=4.30.0
Requires-Dist: torch>=2.0.0
Requires-Dist: requests>=2.28.0
Requires-Dist: python-dotenv>=1.0.0
Requires-Dist: rich>=13.0.0
Requires-Dist: typer>=0.9.0
Requires-Dist: aiohttp>=3.9.0
Provides-Extra: dev
Requires-Dist: pytest>=7.4.0; extra == "dev"
Requires-Dist: pytest-cov>=4.1.0; extra == "dev"
Requires-Dist: pytest-asyncio>=0.21.0; extra == "dev"
Requires-Dist: pytest-benchmark>=4.0.0; extra == "dev"
Requires-Dist: black>=23.7.0; extra == "dev"
Requires-Dist: isort>=5.12.0; extra == "dev"
Requires-Dist: ruff>=0.0.280; extra == "dev"
Requires-Dist: mypy>=1.5.0; extra == "dev"
Requires-Dist: types-requests; extra == "dev"
Dynamic: license-file
